{
  "version": "1.0",
  "last_updated": "07-2025",
  "characters": [
    {
      "name": "Tung Tung Sahur",
      "scale": 1
    },
    {
      "name": "Tralalero Tralala",
      "scale": 0.911089
    },
    {
      "name": "Ballerina Capuchina",
      "scale": 0.92834
    },
    {
      "name": "Capuchino Asesino",
      "scale": 0.363316
    },
    {
      "name": "Expressona",
      "scale": 0.962305
    },
    {
      "name": "Tung Tung Sahur Grua",
      "scale": 1.48811
    },
    {
      "name": "Tralalero Tralala Car",
      "scale": 1.13334
    },
    {
      "name": "Balerina Capuchina Car",
      "scale": 1.53902
    },
    {
      "name": "Expressona Car",
      "scale": 1.80996
    },
    {
      "name": "Profesor School",
      "scale": 0.69493
    },
    {
      "name": "Tatata Sahur",
      "scale": 0.775662
    },
    {
      "name": "Carapibelo Cocosini",
      "scale": 0.804093
    },
    {
      "name": "Tripi tropi",
      "scale": 0.907396
    },
    {
      "name": "Bombardini Gusini",
      "scale": 0.56623
    },
    {
      "name": "Bombardero Crocodilo",
      "scale": 0.74449
    },
    {
      "name": "Boneca Ambalabu",
      "scale": 1.07099
    },
    {
      "name": "Udin din din din",
      "scale": 0.976308
    },
    {
      "name": "Garamadan Salt",
      "scale": 0.959176
    },
     {
      "name": "Garamadan Honey",
      "scale": 0.973538
    },
    {
      "name": "Saturno Saturnita",
      "scale": 1.05601
    },
     {
      "name": "Jirafa Celeste",
      "scale": 1.14314
    },
    {
      "name": "Frigo Camello",
      "scale": 1.48197
    },
    {
      "name": "Lirili Larila",
      "scale": 0.553402
    },
    {
      "name": "Brr Brr Patapim",
      "scale": 1.88227
    },
    {
      "name": "Chicliteira",
      "scale": 1.2699
    },
    {
      "name": "Deer 99 Nights Roblox",
      "scale": 0.559478
    },
    {
      "name": "Nuclearo Dinosaurio",
      "scale": 0.566033
    },
    {
      "name": "Baby Tralalero",
      "scale": 0.354124
    },
    {
      "name": "Baby Saturno saturnita",
      "scale": 2.77683
    }
  ]
}
